{
  " 8107-82260": {
    "start": 82260,
    "data": [
      {
        "route": "52",
        "trip":  8107,
        "time": 82260,
        "longitude": -122.425802,
        "latitude": 37.719192,
        "d_time": -224
      },{
        "route": "52",
        "trip":  8107,
        "time": 81960,
        "longitude": -122.433577,
        "latitude": 37.726162,
        "d_time": -232
      },{
        "route": "52",
        "trip":  8107,
        "time": 81660,
        "longitude": -122.43408,
        "latitude": 37.733488,
        "d_time": -119
      },{
        "route": "52",
        "trip":  8107,
        "time": 81360,
        "longitude": -122.43786,
        "latitude": 37.74359,
        "d_time": -49
      },{
        "route": "52",
        "trip":  8107,
        "time": 81000,
        "longitude": -122.458939,
        "latitude": 37.748157,
        "d_time": 0
      },{
        "route": "52",
        "trip":  8107,
        "time": 37980,
        "longitude": -122.425802,
        "latitude": 37.719192,
        "d_time": 865
      },{
        "route": "52",
        "trip":  8107,
        "time": 37560,
        "longitude": -122.433577,
        "latitude": 37.726162,
        "d_time": 873
      },{
        "route": "52",
        "trip":  8107,
        "time": 37320,
        "longitude": -122.43408,
        "latitude": 37.733488,
        "d_time": 740
      },{
        "route": "52",
        "trip":  8107,
        "time": 37020,
        "longitude": -122.43786,
        "latitude": 37.74359,
        "d_time": 762
      },{
        "route": "52",
        "trip":  8107,
        "time": 36600,
        "longitude": -122.458939,
        "latitude": 37.748157,
        "d_time": 663
      }    ]
  },
  " 8194-39780": {
    "start": 39780,
    "data": [
    {
        "route": "52",
        "trip":  8194,
        "time": 39780,
        "longitude": -122.425802,
        "latitude": 37.719192,
        "d_time": 202
      },{
        "route": "52",
        "trip":  8194,
        "time": 39360,
        "longitude": -122.433577,
        "latitude": 37.726162,
        "d_time": 256
      },{
        "route": "52",
        "trip":  8194,
        "time": 39120,
        "longitude": -122.43408,
        "latitude": 37.733488,
        "d_time": 201
      },{
        "route": "52",
        "trip":  8194,
        "time": 38820,
        "longitude": -122.43786,
        "latitude": 37.74359,
        "d_time": 147
      },{
        "route": "52",
        "trip":  8194,
        "time": 38400,
        "longitude": -122.458939,
        "latitude": 37.748157,
        "d_time": 103
      }    ]
  },
  " 8107-41580": {
    "start": 41580,
    "data": [
    {
        "route": "52",
        "trip":  8107,
        "time": 41580,
        "longitude": -122.425802,
        "latitude": 37.719192,
        "d_time": 1017
      },{
        "route": "52",
        "trip":  8107,
        "time": 41160,
        "longitude": -122.433577,
        "latitude": 37.726162,
        "d_time": 1034
      },{
        "route": "52",
        "trip":  8107,
        "time": 40920,
        "longitude": -122.43408,
        "latitude": 37.733488,
        "d_time": 960
      },{
        "route": "52",
        "trip":  8107,
        "time": 40560,
        "longitude": -122.43786,
        "latitude": 37.74359,
        "d_time": 967
      },{
        "route": "52",
        "trip":  8107,
        "time": 40200,
        "longitude": -122.458939,
        "latitude": 37.748157,
        "d_time": 857
      }    ]
  },
  " 8194-86580": {
    "start": 86580,
    "data": [
    {
        "route": "52",
        "trip":  8194,
        "time": 86580,
        "longitude": -122.425802,
        "latitude": 37.719192,
        "d_time": -43444
      },{
        "route": "52",
        "trip":  8194,
        "time": 42960,
        "longitude": -122.433577,
        "latitude": 37.726162,
        "d_time": -162
      },{
        "route": "52",
        "trip":  8194,
        "time": 42720,
        "longitude": -122.43408,
        "latitude": 37.733488,
        "d_time": -170
      },{
        "route": "52",
        "trip":  8194,
        "time": 42360,
        "longitude": -122.43786,
        "latitude": 37.74359,
        "d_time": -36
      },{
        "route": "52",
        "trip":  8194,
        "time": 42000,
        "longitude": -122.458939,
        "latitude": 37.748157,
        "d_time": 10
      }    ]
  },
  " 8107-88380": {
    "start": 88380,
    "data": [
    {
        "route": "52",
        "trip":  8107,
        "time": 88380,
        "longitude": -122.425802,
        "latitude": 37.719192,
        "d_time": 1327
      },{
        "route": "52",
        "trip":  8107,
        "time": 87960,
        "longitude": -122.433577,
        "latitude": 37.726162,
        "d_time": 1343
      },{
        "route": "52",
        "trip":  8107,
        "time": 87720,
        "longitude": -122.43408,
        "latitude": 37.733488,
        "d_time": 1340
      },{
        "route": "52",
        "trip":  8107,
        "time": 87360,
        "longitude": -122.43786,
        "latitude": 37.74359,
        "d_time": 1330
      },{
        "route": "52",
        "trip":  8107,
        "time": 87000,
        "longitude": -122.458939,
        "latitude": 37.748157,
        "d_time": 1167
      }    ]
  },
  " 8194-46980": {
    "start": 46980,
    "data": [
    {
        "route": "52",
        "trip":  8194,
        "time": 46980,
        "longitude": -122.425802,
        "latitude": 37.719192,
        "d_time": 208
      },{
        "route": "52",
        "trip":  8194,
        "time": 89760,
        "longitude": -122.433577,
        "latitude": 37.726162,
        "d_time": -42942
      },{
        "route": "52",
        "trip":  8194,
        "time": 89520,
        "longitude": -122.43408,
        "latitude": 37.733488,
        "d_time": 175
      },{
        "route": "52",
        "trip":  8194,
        "time": 89160,
        "longitude": -122.43786,
        "latitude": 37.74359,
        "d_time": 212
      },{
        "route": "52",
        "trip":  8194,
        "time": 88800,
        "longitude": -122.458939,
        "latitude": 37.748157,
        "d_time": 10
      }    ]
  },
  " 8107-48780": {
    "start": 48780,
    "data": [
    {
        "route": "52",
        "trip":  8107,
        "time": 48780,
        "longitude": -122.425802,
        "latitude": 37.719192,
        "d_time": 1552
      },{
        "route": "52",
        "trip":  8107,
        "time": 48360,
        "longitude": -122.433577,
        "latitude": 37.726162,
        "d_time": 1463
      },{
        "route": "52",
        "trip":  8107,
        "time": 48120,
        "longitude": -122.43408,
        "latitude": 37.733488,
        "d_time": 1342
      },{
        "route": "52",
        "trip":  8107,
        "time": 47760,
        "longitude": -122.43786,
        "latitude": 37.74359,
        "d_time": 1241
      },{
        "route": "52",
        "trip":  8107,
        "time": 47400,
        "longitude": -122.458939,
        "latitude": 37.748157,
        "d_time": 1203
      }    ]
  },
  " 8194-28380": {
    "start": 28380,
    "data": [
    {
        "route": "52",
        "trip":  8194,
        "time": 28380,
        "longitude": -122.425802,
        "latitude": 37.719192,
        "d_time": 616
      },{
        "route": "52",
        "trip":  8194,
        "time": 28020,
        "longitude": -122.433577,
        "latitude": 37.726162,
        "d_time": 567
      },{
        "route": "52",
        "trip":  8194,
        "time": 27780,
        "longitude": -122.43408,
        "latitude": 37.733488,
        "d_time": 240
      },{
        "route": "52",
        "trip":  8194,
        "time": 27420,
        "longitude": -122.43786,
        "latitude": 37.74359,
        "d_time": 202
      },{
        "route": "52",
        "trip":  8194,
        "time": 27000,
        "longitude": -122.458939,
        "latitude": 37.748157,
        "d_time": 70
      }    ]
  },
  " 8152-29700": {
    "start": 29700,
    "data": [
    {
        "route": "52",
        "trip":  8152,
        "time": 29700,
        "longitude": -122.425802,
        "latitude": 37.719192,
        "d_time": 986
      },{
        "route": "52",
        "trip":  8152,
        "time": 29340,
        "longitude": -122.433577,
        "latitude": 37.726162,
        "d_time": 957
      },{
        "route": "52",
        "trip":  8152,
        "time": 29040,
        "longitude": -122.43408,
        "latitude": 37.733488,
        "d_time": 482
      },{
        "route": "52",
        "trip":  8152,
        "time": 28680,
        "longitude": -122.43786,
        "latitude": 37.74359,
        "d_time": 261
      },{
        "route": "52",
        "trip":  8152,
        "time": 28200,
        "longitude": -122.458939,
        "latitude": 37.748157,
        "d_time": 40
      }    ]
  },
  " 8107-30900": {
    "start": 30900,
    "data": [
    {
        "route": "52",
        "trip":  8107,
        "time": 30900,
        "longitude": -122.425802,
        "latitude": 37.719192,
        "d_time": 1342
      },{
        "route": "52",
        "trip":  8107,
        "time": 30540,
        "longitude": -122.433577,
        "latitude": 37.726162,
        "d_time": 1302
      },{
        "route": "52",
        "trip":  8107,
        "time": 30240,
        "longitude": -122.43408,
        "latitude": 37.733488,
        "d_time": 1323
      },{
        "route": "52",
        "trip":  8107,
        "time": 29880,
        "longitude": -122.43786,
        "latitude": 37.74359,
        "d_time": 1263
      },{
        "route": "52",
        "trip":  8107,
        "time": 29400,
        "longitude": -122.458939,
        "latitude": 37.748157,
        "d_time": 1217
      }    ]
  },
  " 8194-50700": {
    "start": 50700,
    "data": [
    {
        "route": "52",
        "trip":  8194,
        "time": 50700,
        "longitude": -122.425802,
        "latitude": 37.719192,
        "d_time": -12
      },{
        "route": "52",
        "trip":  8194,
        "time": 50280,
        "longitude": -122.433577,
        "latitude": 37.726162,
        "d_time": 78
      },{
        "route": "52",
        "trip":  8194,
        "time": 49980,
        "longitude": -122.43408,
        "latitude": 37.733488,
        "d_time": 140
      },{
        "route": "52",
        "trip":  8194,
        "time": 49620,
        "longitude": -122.43786,
        "latitude": 37.74359,
        "d_time": 133
      },{
        "route": "52",
        "trip":  8194,
        "time": 49200,
        "longitude": -122.458939,
        "latitude": 37.748157,
        "d_time": 48
      }    ]
  },
  " 8107-52500": {
    "start": 52500,
    "data": [
    {
        "route": "52",
        "trip":  8107,
        "time": 52500,
        "longitude": -122.425802,
        "latitude": 37.719192,
        "d_time": 1128
      },{
        "route": "52",
        "trip":  8107,
        "time": 52080,
        "longitude": -122.433577,
        "latitude": 37.726162,
        "d_time": 984
      },{
        "route": "52",
        "trip":  8107,
        "time": 51780,
        "longitude": -122.43408,
        "latitude": 37.733488,
        "d_time": 950
      },{
        "route": "52",
        "trip":  8107,
        "time": 51420,
        "longitude": -122.43786,
        "latitude": 37.74359,
        "d_time": 873
      },{
        "route": "52",
        "trip":  8107,
        "time": 51000,
        "longitude": -122.458939,
        "latitude": 37.748157,
        "d_time": 795
      }    ]
  },
  " 8194-54420": {
    "start": 54420,
    "data": [
    {
        "route": "52",
        "trip":  8194,
        "time": 54420,
        "longitude": -122.425802,
        "latitude": 37.719192,
        "d_time": -84
      },{
        "route": "52",
        "trip":  8194,
        "time": 54000,
        "longitude": -122.433577,
        "latitude": 37.726162,
        "d_time": -60
      },{
        "route": "52",
        "trip":  8194,
        "time": 53640,
        "longitude": -122.43408,
        "latitude": 37.733488,
        "d_time": 25
      },{
        "route": "52",
        "trip":  8194,
        "time": 53280,
        "longitude": -122.43786,
        "latitude": 37.74359,
        "d_time": -69
      },{
        "route": "52",
        "trip":  8194,
        "time": 52800,
        "longitude": -122.458939,
        "latitude": 37.748157,
        "d_time": -42
      }    ]
  },
  " 8107-56220": {
    "start": 56220,
    "data": [
    {
        "route": "52",
        "trip":  8107,
        "time": 56220,
        "longitude": -122.425802,
        "latitude": 37.719192,
        "d_time": 1416
      },{
        "route": "52",
        "trip":  8107,
        "time": 55800,
        "longitude": -122.433577,
        "latitude": 37.726162,
        "d_time": 1377
      },{
        "route": "52",
        "trip":  8107,
        "time": 54600,
        "longitude": -122.458939,
        "latitude": 37.748157,
        "d_time": 1542
      }    ]
  },
  " 8194-58020": {
    "start": 58020,
    "data": [
    {
        "route": "52",
        "trip":  8194,
        "time": 58020,
        "longitude": -122.425802,
        "latitude": 37.719192,
        "d_time": 2
      },{
        "route": "52",
        "trip":  8194,
        "time": 57600,
        "longitude": -122.433577,
        "latitude": 37.726162,
        "d_time": 18
      },{
        "route": "52",
        "trip":  8194,
        "time": 57240,
        "longitude": -122.43408,
        "latitude": 37.733488,
        "d_time": 6
      },{
        "route": "52",
        "trip":  8194,
        "time": 56880,
        "longitude": -122.43786,
        "latitude": 37.74359,
        "d_time": -62
      },{
        "route": "52",
        "trip":  8194,
        "time": 56400,
        "longitude": -122.458939,
        "latitude": 37.748157,
        "d_time": -132
      }    ]
  },
  " 8107-60420": {
    "start": 60420,
    "data": [
    {
        "route": "52",
        "trip":  8107,
        "time": 60420,
        "longitude": -122.425802,
        "latitude": 37.719192,
        "d_time": 1306
      },{
        "route": "52",
        "trip":  8107,
        "time": 60000,
        "longitude": -122.433577,
        "latitude": 37.726162,
        "d_time": 1293
      },{
        "route": "52",
        "trip":  8107,
        "time": 59640,
        "longitude": -122.43408,
        "latitude": 37.733488,
        "d_time": 1293
      },{
        "route": "52",
        "trip":  8107,
        "time": 59280,
        "longitude": -122.43786,
        "latitude": 37.74359,
        "d_time": 1272
      },{
        "route": "52",
        "trip":  8107,
        "time": 58800,
        "longitude": -122.458939,
        "latitude": 37.748157,
        "d_time": 1194
      },{
        "route": "52",
        "trip":  8107,
        "time": 64020,
        "longitude": -122.425802,
        "latitude": 37.719192,
        "d_time": 567
      },{
        "route": "52",
        "trip":  8107,
        "time": 63600,
        "longitude": -122.433577,
        "latitude": 37.726162,
        "d_time": 570
      },{
        "route": "52",
        "trip":  8107,
        "time": 63240,
        "longitude": -122.43408,
        "latitude": 37.733488,
        "d_time": 628
      },{
        "route": "52",
        "trip":  8107,
        "time": 62880,
        "longitude": -122.43786,
        "latitude": 37.74359,
        "d_time": 518
      }    ]
  },
  " 8194-65220": {
    "start": 65220,
    "data": [
    {
        "route": "52",
        "trip":  8194,
        "time": 65220,
        "longitude": -122.425802,
        "latitude": 37.719192,
        "d_time": 746
      },{
        "route": "52",
        "trip":  8194,
        "time": 64800,
        "longitude": -122.433577,
        "latitude": 37.726162,
        "d_time": 693
      },{
        "route": "52",
        "trip":  8194,
        "time": 64440,
        "longitude": -122.43408,
        "latitude": 37.733488,
        "d_time": 631
      },{
        "route": "52",
        "trip":  8194,
        "time": 64080,
        "longitude": -122.43786,
        "latitude": 37.74359,
        "d_time": 408
      },{
        "route": "52",
        "trip":  8194,
        "time": 63600,
        "longitude": -122.458939,
        "latitude": 37.748157,
        "d_time": 357
      }    ]
  },
  " 8107-68100": {
    "start": 68100,
    "data": [
    {
        "route": "52",
        "trip":  8107,
        "time": 68100,
        "longitude": -122.425802,
        "latitude": 37.719192,
        "d_time": 554
      },{
        "route": "52",
        "trip":  8107,
        "time": 67740,
        "longitude": -122.433577,
        "latitude": 37.726162,
        "d_time": 505
      },{
        "route": "52",
        "trip":  8107,
        "time": 67380,
        "longitude": -122.43408,
        "latitude": 37.733488,
        "d_time": 580
      },{
        "route": "52",
        "trip":  8107,
        "time": 67080,
        "longitude": -122.43786,
        "latitude": 37.74359,
        "d_time": 104
      },{
        "route": "52",
        "trip":  8107,
        "time": 66600,
        "longitude": -122.458939,
        "latitude": 37.748157,
        "d_time": 90
      },{
        "route": "52",
        "trip":  8107,
        "time": 71460,
        "longitude": -122.425802,
        "latitude": 37.719192,
        "d_time": 326
      },{
        "route": "52",
        "trip":  8107,
        "time": 71160,
        "longitude": -122.433577,
        "latitude": 37.726162,
        "d_time": 244
      },{
        "route": "52",
        "trip":  8107,
        "time": 70860,
        "longitude": -122.43408,
        "latitude": 37.733488,
        "d_time": 263
      },{
        "route": "52",
        "trip":  8107,
        "time": 70560,
        "longitude": -122.43786,
        "latitude": 37.74359,
        "d_time": 215
      },{
        "route": "52",
        "trip":  8107,
        "time": 70200,
        "longitude": -122.458939,
        "latitude": 37.748157,
        "d_time": 122
      },{
        "route": "52",
        "trip":  8107,
        "time": 75060,
        "longitude": -122.425802,
        "latitude": 37.719192,
        "d_time": 95
      },{
        "route": "52",
        "trip":  8107,
        "time": 74760,
        "longitude": -122.433577,
        "latitude": 37.726162,
        "d_time": 16
      },{
        "route": "52",
        "trip":  8107,
        "time": 74460,
        "longitude": -122.43408,
        "latitude": 37.733488,
        "d_time": 60
      },{
        "route": "52",
        "trip":  8107,
        "time": 74160,
        "longitude": -122.43786,
        "latitude": 37.74359,
        "d_time": 49
      },{
        "route": "52",
        "trip":  8107,
        "time": 73800,
        "longitude": -122.458939,
        "latitude": 37.748157,
        "d_time": 39
      }    ]
  },
  " 8194-24180": {
    "start": 24180,
    "data": [
    {
        "route": "52",
        "trip":  8194,
        "time": 24180,
        "longitude": -122.425802,
        "latitude": 37.719192,
        "d_time": -62
      },{
        "route": "52",
        "trip":  8194,
        "time": 23820,
        "longitude": -122.433577,
        "latitude": 37.726162,
        "d_time": -42
      },{
        "route": "52",
        "trip":  8194,
        "time": 23580,
        "longitude": -122.43408,
        "latitude": 37.733488,
        "d_time": -20
      },{
        "route": "52",
        "trip":  8194,
        "time": 23220,
        "longitude": -122.43786,
        "latitude": 37.74359,
        "d_time": 40
      }    ]
  },
  " 8152-25980": {
    "start": 25980,
    "data": [
    {
        "route": "52",
        "trip":  8152,
        "time": 25980,
        "longitude": -122.425802,
        "latitude": 37.719192,
        "d_time": 20
      },{
        "route": "52",
        "trip":  8152,
        "time": 25620,
        "longitude": -122.433577,
        "latitude": 37.726162,
        "d_time": -14
      },{
        "route": "52",
        "trip":  8152,
        "time": 25380,
        "longitude": -122.43408,
        "latitude": 37.733488,
        "d_time": 46
      },{
        "route": "52",
        "trip":  8152,
        "time": 25020,
        "longitude": -122.43786,
        "latitude": 37.74359,
        "d_time": 82
      },{
        "route": "52",
        "trip":  8152,
        "time": 24600,
        "longitude": -122.458939,
        "latitude": 37.748157,
        "d_time": 21
      }    ]
  },
  " 8107-27180": {
    "start": 27180,
    "data": [
    {
        "route": "52",
        "trip":  8107,
        "time": 27180,
        "longitude": -122.425802,
        "latitude": 37.719192,
        "d_time": 530
      },{
        "route": "52",
        "trip":  8107,
        "time": 26820,
        "longitude": -122.433577,
        "latitude": 37.726162,
        "d_time": 513
      },{
        "route": "52",
        "trip":  8107,
        "time": 26580,
        "longitude": -122.43408,
        "latitude": 37.733488,
        "d_time": 413
      },{
        "route": "52",
        "trip":  8107,
        "time": 26220,
        "longitude": -122.43786,
        "latitude": 37.74359,
        "d_time": 315
      },{
        "route": "52",
        "trip":  8107,
        "time": 25800,
        "longitude": -122.458939,
        "latitude": 37.748157,
        "d_time": 182
      }    ]
  },
  " 8194-32100": {
    "start": 32100,
    "data": [
    {
        "route": "52",
        "trip":  8194,
        "time": 32100,
        "longitude": -122.425802,
        "latitude": 37.719192,
        "d_time": 710
      },{
        "route": "52",
        "trip":  8194,
        "time": 31740,
        "longitude": -122.433577,
        "latitude": 37.726162,
        "d_time": 787
      },{
        "route": "52",
        "trip":  8194,
        "time": 31440,
        "longitude": -122.43408,
        "latitude": 37.733488,
        "d_time": 832
      },{
        "route": "52",
        "trip":  8194,
        "time": 31080,
        "longitude": -122.43786,
        "latitude": 37.74359,
        "d_time": 812
      },{
        "route": "52",
        "trip":  8194,
        "time": 30600,
        "longitude": -122.458939,
        "latitude": 37.748157,
        "d_time": 848
      }    ]
  },
  " 8107-34380": {
    "start": 34380,
    "data": [
    {
        "route": "52",
        "trip":  8107,
        "time": 34380,
        "longitude": -122.425802,
        "latitude": 37.719192,
        "d_time": 1210
      },{
        "route": "52",
        "trip":  8107,
        "time": 34020,
        "longitude": -122.433577,
        "latitude": 37.726162,
        "d_time": 1194
      },{
        "route": "52",
        "trip":  8107,
        "time": 33780,
        "longitude": -122.43408,
        "latitude": 37.733488,
        "d_time": 1143
      },{
        "route": "52",
        "trip":  8107,
        "time": 33420,
        "longitude": -122.43786,
        "latitude": 37.74359,
        "d_time": 1203
      },{
        "route": "52",
        "trip":  8107,
        "time": 33000,
        "longitude": -122.458939,
        "latitude": 37.748157,
        "d_time": 985
      }    ]
  },
  " 8194-36180": {
    "start": 36180,
    "data": [
    {
        "route": "52",
        "trip":  8194,
        "time": 36180,
        "longitude": -122.425802,
        "latitude": 37.719192,
        "d_time": 55
      },{
        "route": "52",
        "trip":  8194,
        "time": 35760,
        "longitude": -122.433577,
        "latitude": 37.726162,
        "d_time": 102
      },{
        "route": "52",
        "trip":  8194,
        "time": 35520,
        "longitude": -122.43408,
        "latitude": 37.733488,
        "d_time": -27
      },{
        "route": "52",
        "trip":  8194,
        "time": 35220,
        "longitude": -122.43786,
        "latitude": 37.74359,
        "d_time": -23
      },{
        "route": "52",
        "trip":  8194,
        "time": 34800,
        "longitude": -122.458939,
        "latitude": 37.748157,
        "d_time": 36
      }    ]
  },
  " 8152-33300": {
    "start": 33300,
    "data": [
    {
        "route": "52",
        "trip":  8152,
        "time": 33300,
        "longitude": -122.425802,
        "latitude": 37.719192,
        "d_time": 564
      },{
        "route": "52",
        "trip":  8152,
        "time": 32940,
        "longitude": -122.433577,
        "latitude": 37.726162,
        "d_time": 642
      },{
        "route": "52",
        "trip":  8152,
        "time": 32640,
        "longitude": -122.43408,
        "latitude": 37.733488,
        "d_time": 620
      },{
        "route": "52",
        "trip":  8152,
        "time": 32280,
        "longitude": -122.43786,
        "latitude": 37.74359,
        "d_time": 588
      },{
        "route": "52",
        "trip":  8152,
        "time": 31800,
        "longitude": -122.458939,
        "latitude": 37.748157,
        "d_time": 702
      }    ]
  },
  " 8107-78660": {
    "start": 78660,
    "data": [
    {
        "route": "52",
        "trip":  8107,
        "time": 78660,
        "longitude": -122.425802,
        "latitude": 37.719192,
        "d_time": -1
      },{
        "route": "52",
        "trip":  8107,
        "time": 78360,
        "longitude": -122.433577,
        "latitude": 37.726162,
        "d_time": -47
      },{
        "route": "52",
        "trip":  8107,
        "time": 78060,
        "longitude": -122.43408,
        "latitude": 37.733488,
        "d_time": 46
      },{
        "route": "52",
        "trip":  8107,
        "time": 77760,
        "longitude": -122.43786,
        "latitude": 37.74359,
        "d_time": 33
      },{
        "route": "52",
        "trip":  8107,
        "time": 77400,
        "longitude": -122.458939,
        "latitude": 37.748157,
        "d_time": 0
      }    ]
  },
  " 8194-61620": {
    "start": 61620,
    "data": [
    {
        "route": "52",
        "trip":  8194,
        "time": 61620,
        "longitude": -122.425802,
        "latitude": 37.719192,
        "d_time": -222
      },{
        "route": "52",
        "trip":  8194,
        "time": 61200,
        "longitude": -122.433577,
        "latitude": 37.726162,
        "d_time": -227
      },{
        "route": "52",
        "trip":  8194,
        "time": 60840,
        "longitude": -122.43408,
        "latitude": 37.733488,
        "d_time": -162
      },{
        "route": "52",
        "trip":  8194,
        "time": 60480,
        "longitude": -122.43786,
        "latitude": 37.74359,
        "d_time": -148
      },{
        "route": "52",
        "trip":  8194,
        "time": 60000,
        "longitude": -122.458939,
        "latitude": 37.748157,
        "d_time": -222
      }    ]
  },
  " 8107-78660": {
    "start": 78660,
    "data": [
    {
        "route": "52",
        "trip":  8107,
        "time": 78660,
        "longitude": -122.425802,
        "latitude": 37.719192,
        "d_time": 0
      },{
        "route": "52",
        "trip":  8107,
        "time": 78900,
        "longitude": -122.43351,
        "latitude": 37.726355,
        "d_time": 16
      },{
        "route": "52",
        "trip":  8107,
        "time": 79140,
        "longitude": -122.434011,
        "latitude": 37.733595,
        "d_time": 60
      },{
        "route": "52",
        "trip":  8107,
        "time": 79440,
        "longitude": -122.43751,
        "latitude": 37.74363,
        "d_time": 24
      },{
        "route": "52",
        "trip":  8107,
        "time": 79860,
        "longitude": -122.458939,
        "latitude": 37.748157,
        "d_time": -120
      },{
        "route": "52",
        "trip":  8107,
        "time": 82260,
        "longitude": -122.425802,
        "latitude": 37.719192,
        "d_time": -179
      },{
        "route": "52",
        "trip":  8107,
        "time": 82500,
        "longitude": -122.43351,
        "latitude": 37.726355,
        "d_time": -132
      },{
        "route": "52",
        "trip":  8107,
        "time": 82740,
        "longitude": -122.434011,
        "latitude": 37.733595,
        "d_time": -98
      },{
        "route": "52",
        "trip":  8107,
        "time": 83040,
        "longitude": -122.43751,
        "latitude": 37.74363,
        "d_time": -83
      },{
        "route": "52",
        "trip":  8107,
        "time": 83460,
        "longitude": -122.458939,
        "latitude": 37.748157,
        "d_time": -146
      }    ]
  },
  " 8194-65220": {
    "start": 65220,
    "data": [
    {
        "route": "52",
        "trip":  8194,
        "time": 65220,
        "longitude": -122.425802,
        "latitude": 37.719192,
        "d_time": 913
      },{
        "route": "52",
        "trip":  8194,
        "time": 65520,
        "longitude": -122.43351,
        "latitude": 37.726355,
        "d_time": 905
      }    ]
  },
  " 8107-68100": {
    "start": 68100,
    "data": [
    {
        "route": "52",
        "trip":  8107,
        "time": 68100,
        "longitude": -122.425802,
        "latitude": 37.719192,
        "d_time": 570
      },{
        "route": "52",
        "trip":  8107,
        "time": 68400,
        "longitude": -122.43351,
        "latitude": 37.726355,
        "d_time": 490
      },{
        "route": "52",
        "trip":  8107,
        "time": 68700,
        "longitude": -122.434011,
        "latitude": 37.733595,
        "d_time": 472
      },{
        "route": "52",
        "trip":  8107,
        "time": 69060,
        "longitude": -122.43751,
        "latitude": 37.74363,
        "d_time": 517
      },{
        "route": "52",
        "trip":  8107,
        "time": 69480,
        "longitude": -122.458939,
        "latitude": 37.748157,
        "d_time": 489
      },{
        "route": "52",
        "trip":  8107,
        "time": 71460,
        "longitude": -122.425802,
        "latitude": 37.719192,
        "d_time": 319
      },{
        "route": "52",
        "trip":  8107,
        "time": 71700,
        "longitude": -122.43351,
        "latitude": 37.726355,
        "d_time": 311
      },{
        "route": "52",
        "trip":  8107,
        "time": 71940,
        "longitude": -122.434011,
        "latitude": 37.733595,
        "d_time": 344
      },{
        "route": "52",
        "trip":  8107,
        "time": 72240,
        "longitude": -122.43751,
        "latitude": 37.74363,
        "d_time": 374
      },{
        "route": "52",
        "trip":  8107,
        "time": 72660,
        "longitude": -122.458939,
        "latitude": 37.748157,
        "d_time": 364
      },{
        "route": "52",
        "trip":  8107,
        "time": 75060,
        "longitude": -122.425802,
        "latitude": 37.719192,
        "d_time": 90
      },{
        "route": "52",
        "trip":  8107,
        "time": 75300,
        "longitude": -122.43351,
        "latitude": 37.726355,
        "d_time": 66
      },{
        "route": "52",
        "trip":  8107,
        "time": 75540,
        "longitude": -122.434011,
        "latitude": 37.733595,
        "d_time": 60
      },{
        "route": "52",
        "trip":  8107,
        "time": 75840,
        "longitude": -122.43751,
        "latitude": 37.74363,
        "d_time": 109
      },{
        "route": "52",
        "trip":  8107,
        "time": 76260,
        "longitude": -122.458939,
        "latitude": 37.748157,
        "d_time": 59
      },{
        "route": "52",
        "trip":  8107,
        "time": 37980,
        "longitude": -122.425802,
        "latitude": 37.719192,
        "d_time": 1147
      },{
        "route": "52",
        "trip":  8107,
        "time": 38280,
        "longitude": -122.43351,
        "latitude": 37.726355,
        "d_time": 1269
      },{
        "route": "52",
        "trip":  8107,
        "time": 38520,
        "longitude": -122.434011,
        "latitude": 37.733595,
        "d_time": 1362
      },{
        "route": "52",
        "trip":  8107,
        "time": 38880,
        "longitude": -122.43751,
        "latitude": 37.74363,
        "d_time": 1367
      },{
        "route": "52",
        "trip":  8107,
        "time": 39360,
        "longitude": -122.458939,
        "latitude": 37.748157,
        "d_time": 1200
      }    ]
  },
  " 8194-28380": {
    "start": 28380,
    "data": [
    {
        "route": "52",
        "trip":  8194,
        "time": 28380,
        "longitude": -122.425802,
        "latitude": 37.719192,
        "d_time": 612
      },{
        "route": "52",
        "trip":  8194,
        "time": 28740,
        "longitude": -122.43351,
        "latitude": 37.726355,
        "d_time": 626
      },{
        "route": "52",
        "trip":  8194,
        "time": 29100,
        "longitude": -122.434011,
        "latitude": 37.733595,
        "d_time": 1315
      },{
        "route": "52",
        "trip":  8194,
        "time": 29460,
        "longitude": -122.43751,
        "latitude": 37.74363,
        "d_time": 1321
      },{
        "route": "52",
        "trip":  8194,
        "time": 29940,
        "longitude": -122.458939,
        "latitude": 37.748157,
        "d_time": 1323
      }    ]
  },
  " 8152-29700": {
    "start": 29700,
    "data": [
    {
        "route": "52",
        "trip":  8152,
        "time": 29700,
        "longitude": -122.425802,
        "latitude": 37.719192,
        "d_time": 948
      },{
        "route": "52",
        "trip":  8152,
        "time": 30060,
        "longitude": -122.43351,
        "latitude": 37.726355,
        "d_time": 945
      },{
        "route": "52",
        "trip":  8152,
        "time": 30420,
        "longitude": -122.434011,
        "latitude": 37.733595,
        "d_time": 1305
      },{
        "route": "52",
        "trip":  8152,
        "time": 30780,
        "longitude": -122.43751,
        "latitude": 37.74363,
        "d_time": 1203
      },{
        "route": "52",
        "trip":  8152,
        "time": 31260,
        "longitude": -122.458939,
        "latitude": 37.748157,
        "d_time": 1175
      }    ]
  },
  " 8107-30900": {
    "start": 30900,
    "data": [
    {
        "route": "52",
        "trip":  8107,
        "time": 30900,
        "longitude": -122.425802,
        "latitude": 37.719192,
        "d_time": 1348
      },{
        "route": "52",
        "trip":  8107,
        "time": 31260,
        "longitude": -122.43351,
        "latitude": 37.726355,
        "d_time": 1413
      },{
        "route": "52",
        "trip":  8107,
        "time": 31620,
        "longitude": -122.434011,
        "latitude": 37.733595,
        "d_time": 1369
      },{
        "route": "52",
        "trip":  8107,
        "time": 31980,
        "longitude": -122.43751,
        "latitude": 37.74363,
        "d_time": 1419
      },{
        "route": "52",
        "trip":  8107,
        "time": 32460,
        "longitude": -122.458939,
        "latitude": 37.748157,
        "d_time": 1426
      }    ]
  },
  " 8194-32100": {
    "start": 32100,
    "data": [
    {
        "route": "52",
        "trip":  8194,
        "time": 32100,
        "longitude": -122.425802,
        "latitude": 37.719192,
        "d_time": 697
      },{
        "route": "52",
        "trip":  8194,
        "time": 32460,
        "longitude": -122.43351,
        "latitude": 37.726355,
        "d_time": 609
      },{
        "route": "52",
        "trip":  8194,
        "time": 32820,
        "longitude": -122.434011,
        "latitude": 37.733595,
        "d_time": 560
      },{
        "route": "52",
        "trip":  8194,
        "time": 33180,
        "longitude": -122.43751,
        "latitude": 37.74363,
        "d_time": 546
      },{
        "route": "52",
        "trip":  8194,
        "time": 33660,
        "longitude": -122.458939,
        "latitude": 37.748157,
        "d_time": 444
      }    ]
  },
  " 8152-22260": {
    "start": 22260,
    "data": [
    {
        "route": "52",
        "trip":  8152,
        "time": 22260,
        "longitude": -122.425802,
        "latitude": 37.719192,
        "d_time": 31
      },{
        "route": "52",
        "trip":  8152,
        "time": 22560,
        "longitude": -122.43351,
        "latitude": 37.726355,
        "d_time": 118
      },{
        "route": "52",
        "trip":  8152,
        "time": 22800,
        "longitude": -122.434011,
        "latitude": 37.733595,
        "d_time": 116
      },{
        "route": "52",
        "trip":  8152,
        "time": 23160,
        "longitude": -122.43751,
        "latitude": 37.74363,
        "d_time": 32
      },{
        "route": "52",
        "trip":  8152,
        "time": 23580,
        "longitude": -122.458939,
        "latitude": 37.748157,
        "d_time": 6
      }    ]
  },
  " 8194-24180": {
    "start": 24180,
    "data": [
    {
        "route": "52",
        "trip":  8194,
        "time": 24180,
        "longitude": -122.425802,
        "latitude": 37.719192,
        "d_time": -148
      },{
        "route": "52",
        "trip":  8194,
        "time": 24480,
        "longitude": -122.43351,
        "latitude": 37.726355,
        "d_time": -64
      },{
        "route": "52",
        "trip":  8194,
        "time": 24780,
        "longitude": -122.434011,
        "latitude": 37.733595,
        "d_time": -10
      },{
        "route": "52",
        "trip":  8194,
        "time": 25140,
        "longitude": -122.43751,
        "latitude": 37.74363,
        "d_time": 12
      },{
        "route": "52",
        "trip":  8194,
        "time": 25620,
        "longitude": -122.458939,
        "latitude": 37.748157,
        "d_time": -7
      }    ]
  },
  " 8107-34500": {
    "start": 34500,
    "data": [
    {
        "route": "52",
        "trip":  8107,
        "time": 34500,
        "longitude": -122.425802,
        "latitude": 37.719192,
        "d_time": 1111
      },{
        "route": "52",
        "trip":  8107,
        "time": 34800,
        "longitude": -122.43351,
        "latitude": 37.726355,
        "d_time": 1223
      },{
        "route": "52",
        "trip":  8107,
        "time": 35040,
        "longitude": -122.434011,
        "latitude": 37.733595,
        "d_time": 1283
      },{
        "route": "52",
        "trip":  8107,
        "time": 35400,
        "longitude": -122.43751,
        "latitude": 37.74363,
        "d_time": 1378
      },{
        "route": "52",
        "trip":  8107,
        "time": 35880,
        "longitude": -122.458939,
        "latitude": 37.748157,
        "d_time": 1276
      }    ]
  },
  " 8194-36180": {
    "start": 36180,
    "data": [
    {
        "route": "52",
        "trip":  8194,
        "time": 36180,
        "longitude": -122.425802,
        "latitude": 37.719192,
        "d_time": 71
      },{
        "route": "52",
        "trip":  8194,
        "time": 36480,
        "longitude": -122.43351,
        "latitude": 37.726355,
        "d_time": 40
      },{
        "route": "52",
        "trip":  8194,
        "time": 36720,
        "longitude": -122.434011,
        "latitude": 37.733595,
        "d_time": 102
      },{
        "route": "52",
        "trip":  8194,
        "time": 37080,
        "longitude": -122.43751,
        "latitude": 37.74363,
        "d_time": 29
      },{
        "route": "52",
        "trip":  8194,
        "time": 37560,
        "longitude": -122.458939,
        "latitude": 37.748157,
        "d_time": -98
      }    ]
  },
  " 8152-25980": {
    "start": 25980,
    "data": [
    {
        "route": "52",
        "trip":  8152,
        "time": 25980,
        "longitude": -122.425802,
        "latitude": 37.719192,
        "d_time": 4
      },{
        "route": "52",
        "trip":  8152,
        "time": 26280,
        "longitude": -122.43351,
        "latitude": 37.726355,
        "d_time": 136
      },{
        "route": "52",
        "trip":  8152,
        "time": 26580,
        "longitude": -122.434011,
        "latitude": 37.733595,
        "d_time": 245
      },{
        "route": "52",
        "trip":  8152,
        "time": 26940,
        "longitude": -122.43751,
        "latitude": 37.74363,
        "d_time": 216
      },{
        "route": "52",
        "trip":  8152,
        "time": 27420,
        "longitude": -122.458939,
        "latitude": 37.748157,
        "d_time": 380
      }    ]
  },
  " 8107-27180": {
    "start": 27180,
    "data": [
    {
        "route": "52",
        "trip":  8107,
        "time": 27180,
        "longitude": -122.425802,
        "latitude": 37.719192,
        "d_time": 522
      },{
        "route": "52",
        "trip":  8107,
        "time": 27480,
        "longitude": -122.43351,
        "latitude": 37.726355,
        "d_time": 719
      },{
        "route": "52",
        "trip":  8107,
        "time": 27780,
        "longitude": -122.434011,
        "latitude": 37.733595,
        "d_time": 1626
      },{
        "route": "52",
        "trip":  8107,
        "time": 28140,
        "longitude": -122.43751,
        "latitude": 37.74363,
        "d_time": 1622
      },{
        "route": "52",
        "trip":  8107,
        "time": 28620,
        "longitude": -122.458939,
        "latitude": 37.748157,
        "d_time": 1593
      }    ]
  },
  " 8194-39780": {
    "start": 39780,
    "data": [
    {
        "route": "52",
        "trip":  8194,
        "time": 39780,
        "longitude": -122.425802,
        "latitude": 37.719192,
        "d_time": 197
      },{
        "route": "52",
        "trip":  8194,
        "time": 40080,
        "longitude": -122.43351,
        "latitude": 37.726355,
        "d_time": 271
      },{
        "route": "52",
        "trip":  8194,
        "time": 40320,
        "longitude": -122.434011,
        "latitude": 37.733595,
        "d_time": 340
      },{
        "route": "52",
        "trip":  8194,
        "time": 40680,
        "longitude": -122.43751,
        "latitude": 37.74363,
        "d_time": 296
      },{
        "route": "52",
        "trip":  8194,
        "time": 41160,
        "longitude": -122.458939,
        "latitude": 37.748157,
        "d_time": 219
      }    ]
  },
  " 8107-41580": {
    "start": 41580,
    "data": [
    {
        "route": "52",
        "trip":  8107,
        "time": 41580,
        "longitude": -122.425802,
        "latitude": 37.719192,
        "d_time": 1552
      },{
        "route": "52",
        "trip":  8107,
        "time": 41880,
        "longitude": -122.43351,
        "latitude": 37.726355,
        "d_time": 44839
      },{
        "route": "52",
        "trip":  8107,
        "time": 42120,
        "longitude": -122.434011,
        "latitude": 37.733595,
        "d_time": 44913
      },{
        "route": "52",
        "trip":  8107,
        "time": 42480,
        "longitude": -122.43751,
        "latitude": 37.74363,
        "d_time": 44877
      },{
        "route": "52",
        "trip":  8107,
        "time": 42960,
        "longitude": -122.458939,
        "latitude": 37.748157,
        "d_time": 44793
      },{
        "route": "52",
        "trip":  8107,
        "time": 88380,
        "longitude": -122.425802,
        "latitude": 37.719192,
        "d_time": -41523
      },{
        "route": "52",
        "trip":  8107,
        "time": 88680,
        "longitude": -122.43351,
        "latitude": 37.726355,
        "d_time": -41386
      },{
        "route": "52",
        "trip":  8107,
        "time": 88920,
        "longitude": -122.434011,
        "latitude": 37.733595,
        "d_time": -41327
      },{
        "route": "52",
        "trip":  8107,
        "time": 89280,
        "longitude": -122.43751,
        "latitude": 37.74363,
        "d_time": -41269
      },{
        "route": "52",
        "trip":  8107,
        "time": 89760,
        "longitude": -122.458939,
        "latitude": 37.748157,
        "d_time": -41346
      }    ]
  },
  " 8152-33300": {
    "start": 33300,
    "data": [
    {
        "route": "52",
        "trip":  8152,
        "time": 33300,
        "longitude": -122.425802,
        "latitude": 37.719192,
        "d_time": 564
      },{
        "route": "52",
        "trip":  8152,
        "time": 33600,
        "longitude": -122.43351,
        "latitude": 37.726355,
        "d_time": 600
      },{
        "route": "52",
        "trip":  8152,
        "time": 33840,
        "longitude": -122.434011,
        "latitude": 37.733595,
        "d_time": 712
      },{
        "route": "52",
        "trip":  8152,
        "time": 34200,
        "longitude": -122.43751,
        "latitude": 37.74363,
        "d_time": 628
      }    ]
  },
  " 8194-46980": {
    "start": 46980,
    "data": [
    {
        "route": "52",
        "trip":  8194,
        "time": 46980,
        "longitude": -122.425802,
        "latitude": 37.719192,
        "d_time": 257
      },{
        "route": "52",
        "trip":  8194,
        "time": 47280,
        "longitude": -122.43351,
        "latitude": 37.726355,
        "d_time": 258
      },{
        "route": "52",
        "trip":  8194,
        "time": 47520,
        "longitude": -122.434011,
        "latitude": 37.733595,
        "d_time": 292
      },{
        "route": "52",
        "trip":  8194,
        "time": 47880,
        "longitude": -122.43751,
        "latitude": 37.74363,
        "d_time": 267
      },{
        "route": "52",
        "trip":  8194,
        "time": 48360,
        "longitude": -122.458939,
        "latitude": 37.748157,
        "d_time": 139
      }    ]
  },
  " 8107-48780": {
    "start": 48780,
    "data": [
    {
        "route": "52",
        "trip":  8107,
        "time": 48780,
        "longitude": -122.425802,
        "latitude": 37.719192,
        "d_time": 1599
      },{
        "route": "52",
        "trip":  8107,
        "time": 49080,
        "longitude": -122.43351,
        "latitude": 37.726355,
        "d_time": 1572
      },{
        "route": "52",
        "trip":  8107,
        "time": 49320,
        "longitude": -122.434011,
        "latitude": 37.733595,
        "d_time": 1533
      },{
        "route": "52",
        "trip":  8107,
        "time": 49680,
        "longitude": -122.43751,
        "latitude": 37.74363,
        "d_time": 1450
      },{
        "route": "52",
        "trip":  8107,
        "time": 50160,
        "longitude": -122.458939,
        "latitude": 37.748157,
        "d_time": 1320
      }    ]
  },
  " 8194-50700": {
    "start": 50700,
    "data": [
    {
        "route": "52",
        "trip":  8194,
        "time": 50700,
        "longitude": -122.425802,
        "latitude": 37.719192,
        "d_time": -13
      },{
        "route": "52",
        "trip":  8194,
        "time": 51000,
        "longitude": -122.43351,
        "latitude": 37.726355,
        "d_time": 138
      },{
        "route": "52",
        "trip":  8194,
        "time": 51240,
        "longitude": -122.434011,
        "latitude": 37.733595,
        "d_time": 169
      },{
        "route": "52",
        "trip":  8194,
        "time": 51600,
        "longitude": -122.43751,
        "latitude": 37.74363,
        "d_time": 152
      },{
        "route": "52",
        "trip":  8194,
        "time": 52080,
        "longitude": -122.458939,
        "latitude": 37.748157,
        "d_time": -12
      }    ]
  },
  " 8107-52500": {
    "start": 52500,
    "data": [
    {
        "route": "52",
        "trip":  8107,
        "time": 52500,
        "longitude": -122.425802,
        "latitude": 37.719192,
        "d_time": 1539
      },{
        "route": "52",
        "trip":  8107,
        "time": 52800,
        "longitude": -122.43351,
        "latitude": 37.726355,
        "d_time": 1597
      },{
        "route": "52",
        "trip":  8107,
        "time": 53040,
        "longitude": -122.434011,
        "latitude": 37.733595,
        "d_time": 1628
      },{
        "route": "52",
        "trip":  8107,
        "time": 53400,
        "longitude": -122.43751,
        "latitude": 37.74363,
        "d_time": 1657
      },{
        "route": "52",
        "trip":  8107,
        "time": 53880,
        "longitude": -122.458939,
        "latitude": 37.748157,
        "d_time": 1719
      }    ]
  },
  " 8194-54420": {
    "start": 54420,
    "data": [
    {
        "route": "52",
        "trip":  8194,
        "time": 54420,
        "longitude": -122.425802,
        "latitude": 37.719192,
        "d_time": -40
      },{
        "route": "52",
        "trip":  8194,
        "time": 54720,
        "longitude": -122.43351,
        "latitude": 37.726355,
        "d_time": 18
      },{
        "route": "52",
        "trip":  8194,
        "time": 55020,
        "longitude": -122.434011,
        "latitude": 37.733595,
        "d_time": 8
      },{
        "route": "52",
        "trip":  8194,
        "time": 55440,
        "longitude": -122.43751,
        "latitude": 37.74363,
        "d_time": -69
      },{
        "route": "52",
        "trip":  8194,
        "time": 55920,
        "longitude": -122.458939,
        "latitude": 37.748157,
        "d_time": -51
      }    ]
  },
  " 8107-56220": {
    "start": 56220,
    "data": [
    {
        "route": "52",
        "trip":  8107,
        "time": 56220,
        "longitude": -122.425802,
        "latitude": 37.719192,
        "d_time": 1930
      },{
        "route": "52",
        "trip":  8107,
        "time": 56520,
        "longitude": -122.43351,
        "latitude": 37.726355,
        "d_time": 1974
      },{
        "route": "52",
        "trip":  8107,
        "time": 56820,
        "longitude": -122.434011,
        "latitude": 37.733595,
        "d_time": 2076
      },{
        "route": "52",
        "trip":  8107,
        "time": 57240,
        "longitude": -122.43751,
        "latitude": 37.74363,
        "d_time": 2073
      },{
        "route": "52",
        "trip":  8107,
        "time": 57720,
        "longitude": -122.458939,
        "latitude": 37.748157,
        "d_time": 2081
      }    ]
  },
  " 8194-58020": {
    "start": 58020,
    "data": [
    {
        "route": "52",
        "trip":  8194,
        "time": 58020,
        "longitude": -122.425802,
        "latitude": 37.719192,
        "d_time": 85
      },{
        "route": "52",
        "trip":  8194,
        "time": 58320,
        "longitude": -122.43351,
        "latitude": 37.726355,
        "d_time": 130
      },{
        "route": "52",
        "trip":  8194,
        "time": 58620,
        "longitude": -122.434011,
        "latitude": 37.733595,
        "d_time": 240
      },{
        "route": "52",
        "trip":  8194,
        "time": 59040,
        "longitude": -122.43751,
        "latitude": 37.74363,
        "d_time": 165
      },{
        "route": "52",
        "trip":  8194,
        "time": 59520,
        "longitude": -122.458939,
        "latitude": 37.748157,
        "d_time": 147
      }    ]
  },
  " 8107-60420": {
    "start": 60420,
    "data": [
    {
        "route": "52",
        "trip":  8107,
        "time": 60420,
        "longitude": -122.425802,
        "latitude": 37.719192,
        "d_time": 1836
      },{
        "route": "52",
        "trip":  8107,
        "time": 60720,
        "longitude": -122.43351,
        "latitude": 37.726355,
        "d_time": 1865
      }    ]
  },
  " 8194-61620": {
    "start": 61620,
    "data": [
    {
        "route": "52",
        "trip":  8194,
        "time": 61620,
        "longitude": -122.425802,
        "latitude": 37.719192,
        "d_time": -223
      },{
        "route": "52",
        "trip":  8194,
        "time": 61920,
        "longitude": -122.43351,
        "latitude": 37.726355,
        "d_time": -156
      },{
        "route": "52",
        "trip":  8194,
        "time": 62220,
        "longitude": -122.434011,
        "latitude": 37.733595,
        "d_time": -12
      },{
        "route": "52",
        "trip":  8194,
        "time": 62640,
        "longitude": -122.43751,
        "latitude": 37.74363,
        "d_time": 49
      },{
        "route": "52",
        "trip":  8194,
        "time": 63120,
        "longitude": -122.458939,
        "latitude": 37.748157,
        "d_time": -72
      }    ]
  },
  " 8107-64020": {
    "start": 64020,
    "data": [
    {
        "route": "52",
        "trip":  8107,
        "time": 64020,
        "longitude": -122.425802,
        "latitude": 37.719192,
        "d_time": 568
      },{
        "route": "52",
        "trip":  8107,
        "time": 64320,
        "longitude": -122.43351,
        "latitude": 37.726355,
        "d_time": 592
      },{
        "route": "52",
        "trip":  8107,
        "time": 64620,
        "longitude": -122.434011,
        "latitude": 37.733595,
        "d_time": 647
      },{
        "route": "52",
        "trip":  8107,
        "time": 65040,
        "longitude": -122.43751,
        "latitude": 37.74363,
        "d_time": 640
      },{
        "route": "52",
        "trip":  8107,
        "time": 65520,
        "longitude": -122.458939,
        "latitude": 37.748157,
        "d_time": 600
      }    ]
  },
  " 8194-86580": {
    "start": 86580,
    "data": [
    {
        "route": "52",
        "trip":  8194,
        "time": 86580,
        "longitude": -122.425802,
        "latitude": 37.719192,
        "d_time": -19
      },{
        "route": "52",
        "trip":  8194,
        "time": 86880,
        "longitude": -122.43351,
        "latitude": 37.726355,
        "d_time": 1
      },{
        "route": "52",
        "trip":  8194,
        "time": 87120,
        "longitude": -122.434011,
        "latitude": 37.733595,
        "d_time": 22
      },{
        "route": "52",
        "trip":  8194,
        "time": 87480,
        "longitude": -122.43751,
        "latitude": 37.74363,
        "d_time": -50
      },{
        "route": "52",
        "trip":  8194,
        "time": 87960,
        "longitude": -122.458939,
        "latitude": 37.748157,
        "d_time": -94
      }    ]
  }
}