{
  " 8302-65100": {
    "start": 65100,
    "data": [
      {
        "route": "31AX",
        "trip":  8302,
        "time": 65100,
        "longitude": -122.397532,
        "latitude": 37.792608,
        "d_time": 0
      },{
        "route": "31AX",
        "trip":  8302,
        "time": 66540,
        "longitude": -122.472227,
        "latitude": 37.776895,
        "d_time": 112
      },{
        "route": "31AX",
        "trip":  8302,
        "time": 67260,
        "longitude": -122.509934,
        "latitude": 37.773321,
        "d_time": 158
      }    ]
  },
  " 8353-59400": {
    "start": 59400,
    "data": [
    {
        "route": "31AX",
        "trip":  8353,
        "time": 59400,
        "longitude": -122.472227,
        "latitude": 37.776895,
        "d_time": 195
      },{
        "route": "31AX",
        "trip":  8353,
        "time": 60120,
        "longitude": -122.509934,
        "latitude": 37.773321,
        "d_time": 200
      }    ]
  },
  " 8355-60600": {
    "start": 60600,
    "data": [
    {
        "route": "31AX",
        "trip":  8355,
        "time": 60600,
        "longitude": -122.397532,
        "latitude": 37.792608,
        "d_time": -37
      },{
        "route": "31AX",
        "trip":  8355,
        "time": 61800,
        "longitude": -122.472227,
        "latitude": 37.776895,
        "d_time": 132
      },{
        "route": "31AX",
        "trip":  8355,
        "time": 62520,
        "longitude": -122.509934,
        "latitude": 37.773321,
        "d_time": 109
      }    ]
  },
  " 8338-61200": {
    "start": 61200,
    "data": [
    {
        "route": "31AX",
        "trip":  8338,
        "time": 61200,
        "longitude": -122.397532,
        "latitude": 37.792608,
        "d_time": -67
      }    ]
  },
  " 8220-61920": {
    "start": 61920,
    "data": [
    {
        "route": "31AX",
        "trip":  8220,
        "time": 61920,
        "longitude": -122.397532,
        "latitude": 37.792608,
        "d_time": 4
      },{
        "route": "31AX",
        "trip":  8220,
        "time": 63180,
        "longitude": -122.472227,
        "latitude": 37.776895,
        "d_time": 450
      },{
        "route": "31AX",
        "trip":  8220,
        "time": 63900,
        "longitude": -122.509934,
        "latitude": 37.773321,
        "d_time": 547
      }    ]
  },
  " 8116-62520": {
    "start": 62520,
    "data": [
    {
        "route": "31AX",
        "trip":  8116,
        "time": 62520,
        "longitude": -122.397532,
        "latitude": 37.792608,
        "d_time": 61
      },{
        "route": "31AX",
        "trip":  8116,
        "time": 63780,
        "longitude": -122.472227,
        "latitude": 37.776895,
        "d_time": 497
      },{
        "route": "31AX",
        "trip":  8116,
        "time": 64500,
        "longitude": -122.509934,
        "latitude": 37.773321,
        "d_time": 557
      }    ]
  },
  " 8350-63120": {
    "start": 63120,
    "data": [
    {
        "route": "31AX",
        "trip":  8350,
        "time": 63120,
        "longitude": -122.397532,
        "latitude": 37.792608,
        "d_time": 26
      },{
        "route": "31AX",
        "trip":  8350,
        "time": 64560,
        "longitude": -122.472227,
        "latitude": 37.776895,
        "d_time": 162
      },{
        "route": "31AX",
        "trip":  8350,
        "time": 65340,
        "longitude": -122.509934,
        "latitude": 37.773321,
        "d_time": 131
      }    ]
  },
  " 8025-63720": {
    "start": 63720,
    "data": [
    {
        "route": "31AX",
        "trip":  8025,
        "time": 63720,
        "longitude": -122.397532,
        "latitude": 37.792608,
        "d_time": -55
      },{
        "route": "31AX",
        "trip":  8025,
        "time": 65400,
        "longitude": -122.472227,
        "latitude": 37.776895,
        "d_time": -146
      },{
        "route": "31AX",
        "trip":  8025,
        "time": 66240,
        "longitude": -122.509934,
        "latitude": 37.773321,
        "d_time": -278
      }    ]
  },
  " 8426-64320": {
    "start": 64320,
    "data": [
    {
        "route": "31AX",
        "trip":  8426,
        "time": 64320,
        "longitude": -122.397532,
        "latitude": 37.792608,
        "d_time": 122
      },{
        "route": "31AX",
        "trip":  8426,
        "time": 66000,
        "longitude": -122.472227,
        "latitude": 37.776895,
        "d_time": 149
      },{
        "route": "31AX",
        "trip":  8426,
        "time": 66840,
        "longitude": -122.509934,
        "latitude": 37.773321,
        "d_time": 123
      }    ]
  },
  " 8119-26580": {
    "start": 26580,
    "data": [
    {
        "route": "31AX",
        "trip":  8119,
        "time": 26580,
        "longitude": -122.397532,
        "latitude": 37.792608,
        "d_time": -237
      },{
        "route": "31AX",
        "trip":  8119,
        "time": 25380,
        "longitude": -122.472411,
        "latitude": 37.776788,
        "d_time": -74
      }    ]
  },
  " 8131-27240": {
    "start": 27240,
    "data": [
    {
        "route": "31AX",
        "trip":  8131,
        "time": 27240,
        "longitude": -122.397532,
        "latitude": 37.792608,
        "d_time": -162
      },{
        "route": "31AX",
        "trip":  8131,
        "time": 26040,
        "longitude": -122.472411,
        "latitude": 37.776788,
        "d_time": 7
      }    ]
  },
  " 2829-27840": {
    "start": 27840,
    "data": [
    {
        "route": "31AX",
        "trip":  2829,
        "time": 27840,
        "longitude": -122.397532,
        "latitude": 37.792608,
        "d_time": 803
      },{
        "route": "31AX",
        "trip":  2829,
        "time": 26640,
        "longitude": -122.472411,
        "latitude": 37.776788,
        "d_time": 393
      }    ]
  },
  " 2832-28680": {
    "start": 28680,
    "data": [
    {
        "route": "31AX",
        "trip":  2832,
        "time": 28680,
        "longitude": -122.397532,
        "latitude": 37.792608,
        "d_time": 268
      },{
        "route": "31AX",
        "trip":  2832,
        "time": 27240,
        "longitude": -122.472411,
        "latitude": 37.776788,
        "d_time": 160
      }    ]
  },
  " 8359-29280": {
    "start": 29280,
    "data": [
    {
        "route": "31AX",
        "trip":  8359,
        "time": 29280,
        "longitude": -122.397532,
        "latitude": 37.792608,
        "d_time": 360
      },{
        "route": "31AX",
        "trip":  8359,
        "time": 27840,
        "longitude": -122.472411,
        "latitude": 37.776788,
        "d_time": 13
      }    ]
  },
  " 8187-30240": {
    "start": 30240,
    "data": [
    {
        "route": "31AX",
        "trip":  8187,
        "time": 30240,
        "longitude": -122.397532,
        "latitude": 37.792608,
        "d_time": 145
      },{
        "route": "31AX",
        "trip":  8187,
        "time": 28440,
        "longitude": -122.472411,
        "latitude": 37.776788,
        "d_time": -59
      }    ]
  },
  " 8165-30840": {
    "start": 30840,
    "data": [
    {
        "route": "31AX",
        "trip":  8165,
        "time": 30840,
        "longitude": -122.397532,
        "latitude": 37.792608,
        "d_time": 660
      },{
        "route": "31AX",
        "trip":  8165,
        "time": 29040,
        "longitude": -122.472411,
        "latitude": 37.776788,
        "d_time": 69
      }    ]
  },
  " 8119-31440": {
    "start": 31440,
    "data": [
    {
        "route": "31AX",
        "trip":  8119,
        "time": 31440,
        "longitude": -122.397532,
        "latitude": 37.792608,
        "d_time": 124
      },{
        "route": "31AX",
        "trip":  8119,
        "time": 29640,
        "longitude": -122.472411,
        "latitude": 37.776788,
        "d_time": 8
      }    ]
  },
  " 8131-31860": {
    "start": 31860,
    "data": [
    {
        "route": "31AX",
        "trip":  8131,
        "time": 31860,
        "longitude": -122.397532,
        "latitude": 37.792608,
        "d_time": 882
      },{
        "route": "31AX",
        "trip":  8131,
        "time": 30240,
        "longitude": -122.472411,
        "latitude": 37.776788,
        "d_time": 127
      }    ]
  },
  " 8017-32460": {
    "start": 32460,
    "data": [
    {
        "route": "31AX",
        "trip":  8017,
        "time": 32460,
        "longitude": -122.397532,
        "latitude": 37.792608,
        "d_time": 779
      },{
        "route": "31AX",
        "trip":  8017,
        "time": 30840,
        "longitude": -122.472411,
        "latitude": 37.776788,
        "d_time": -7
      }    ]
  }
}